LICENSE
README.md
setup.py
bigquery_schema_generator/__init__.py
bigquery_schema_generator/anonymize.py
bigquery_schema_generator/generate_schema.py
bigquery_schema_generator/version.py
bigquery_schema_generator.egg-info/PKG-INFO
bigquery_schema_generator.egg-info/SOURCES.txt
bigquery_schema_generator.egg-info/dependency_links.txt
bigquery_schema_generator.egg-info/entry_points.txt
bigquery_schema_generator.egg-info/top_level.txt