Metadata-Version: 2.1
Name: bigquery-schema-generator
Version: 1.6.1
Summary: BigQuery schema generator from JSON or CSV data
Home-page: https://github.com/bxparks/bigquery-schema-generator
Author: Brian T. Park
Author-email: brian@xparks.net
License: Apache 2.0
Platform: UNKNOWN
Requires-Python: >=3.6
License-File: LICENSE
